repairshopr_api/__init__.py
repairshopr_api/base/__init__.py
repairshopr_api/base/fields.py
repairshopr_api/base/model.py
repairshopr_api/client.py
repairshopr_api/config/__init__.py
repairshopr_api/config/base.py
repairshopr_api/config/display_settings.py
repairshopr_api/config/initialize.py
repairshopr_api/config/sections/__init__.py
repairshopr_api/config/sections/django.py
repairshopr_api/config/sections/repairshopr.py
repairshopr_api/config/serializable.py
repairshopr_api/converters/__init__.py
repairshopr_api/converters/strings.py
repairshopr_api/models/__init__.py
repairshopr_api/models/customer.py
repairshopr_api/models/estimate.py
repairshopr_api/models/invoice.py
repairshopr_api/models/payment.py
repairshopr_api/models/product.py
repairshopr_api/models/ticket.py
repairshopr_api/models/user.py
repairshopr_sync/__init__.py
repairshopr_sync/manage.py
repairshopr_sync/repairshopr_data/__init__.py
repairshopr_sync/repairshopr_data/admin.py
repairshopr_sync/repairshopr_data/apps.py
repairshopr_sync/repairshopr_data/management/__init__.py
repairshopr_sync/repairshopr_data/management/commands/__init__.py
repairshopr_sync/repairshopr_data/management/commands/flush.py
repairshopr_sync/repairshopr_data/management/commands/import_from_repairshopr.py
repairshopr_sync/repairshopr_data/migrations/0001_initial.py
repairshopr_sync/repairshopr_data/migrations/0002_alter_customer_pdf_url.py
repairshopr_sync/repairshopr_data/migrations/0003_alter_customer_pdf_url.py
repairshopr_sync/repairshopr_data/migrations/0004_alter_customer_online_profile_url_and_more.py
repairshopr_sync/repairshopr_data/migrations/0005_alter_estimatelineitem_name.py
repairshopr_sync/repairshopr_data/migrations/0006_alter_invoicelineitem_name.py
repairshopr_sync/repairshopr_data/migrations/0007_alter_payment_invoice_ids.py
repairshopr_sync/repairshopr_data/migrations/0008_alter_ticketcomment_body.py
repairshopr_sync/repairshopr_data/migrations/0009_alter_ticketcomment_body.py
repairshopr_api-0.3.4.dist-info/METADATA
repairshopr_api-0.3.4.dist-info/WHEEL
repairshopr_api-0.3.4.dist-info/entry_points.txt
repairshopr_api-0.3.4.dist-info/RECORD
