Metadata-Version: 2.4
Name: repairshopr-api
Version: 0.3.4
Summary: 
Author: Chris Busillo
Author-email: info@shinycomputers.com
Requires-Python: >=3.11,<4.0
Classifier: Programming Language :: Python :: 3
Classifier: Programming Language :: Python :: 3.11
Classifier: Programming Language :: Python :: 3.12
Classifier: Programming Language :: Python :: 3.13
Classifier: Programming Language :: Python :: 3.14
Provides-Extra: mysql
Provides-Extra: sync
Requires-Dist: django (>=5.0.1,<6.0.0) ; extra == "sync"
Requires-Dist: mysqlclient (>=2.2.1,<3.0.0) ; extra == "mysql" or extra == "sync"
Requires-Dist: pytz (>=2023.3.post1,<2024.0)
Requires-Dist: requests (>=2.31.0,<3.0.0)
Requires-Dist: tenacity (>=8.2.3,<9.0.0)
Requires-Dist: toml (>=0.10.2,<0.11.0)
